vishwa_packages/__init__.py
vishwa_packages/mass_prince.py
vishwa_packages/mass_study.py
vishwa_packages/mass_vishwa.py
vishwa_packages-1.1.dist-info/LICENSE
vishwa_packages-1.1.dist-info/METADATA
vishwa_packages-1.1.dist-info/WHEEL
vishwa_packages-1.1.dist-info/top_level.txt
vishwa_packages-1.1.dist-info/RECORD
