Metadata-Version: 2.1
Name: vishwa_packages
Version: 1.1
Summary: A simple utility package.
Author: Mass Prince 
Author-email: vishwa.automationhub@gmail.com
Classifier: Programming Language :: Python :: 3
Classifier: License :: OSI Approved :: MIT License
Classifier: Operating System :: OS Independent
Requires-Python: >=3.6
License-File: LICENSE
